[
  {
    "ticker": "AAPL",
    "sector": "Technology",
    "asset_class": "Equity",
    "quantity": 10.0,
    "purchase_price": 150.0,
    "current_price": 248.8000030517578
  },
  {
    "ticker": "MSFT",
    "sector": "Technology",
    "asset_class": "Equity",
    "quantity": 5.0,
    "purchase_price": 300.0,
    "current_price": 356.7699890136719
  },
  {
    "ticker": "JPM",
    "sector": "Financials",
    "asset_class": "Equity",
    "quantity": 8.0,
    "purchase_price": 130.0,
    "current_price": 282.8399963378906
  },
  {
    "ticker": "GLD",
    "sector": "Commodities",
    "asset_class": "Alternative",
    "quantity": 3.0,
    "purchase_price": 180.0,
    "current_price": 414.70001220703125
  }
]